{
  "updated": "2026-07-13T20:36:09Z",
  "quotes": {
    "dow": {
      "price": 52498.6406,
      "change": -138.3694,
      "pct": -0.2629
    },
    "sp500": {
      "price": 7515.3398,
      "change": -60.0502,
      "pct": -0.7927
    },
    "nasdaq": {
      "price": 29264.1035,
      "change": -561.0065,
      "pct": -1.881
    },
    "russell": {
      "price": 2953.1663,
      "change": -24.6389,
      "pct": -0.8274
    },
    "vix": {
      "price": 17.16,
      "change": 2.12,
      "pct": 14.0957
    },
    "kospi": {
      "price": 6806.93,
      "change": -669.01,
      "pct": -8.9488
    },
    "kospi200": {
      "price": 1078.78,
      "change": -117.91,
      "pct": -9.853
    },
    "gold": {
      "price": 4006.5,
      "change": -60.8999,
      "pct": -1.4973
    },
    "silver": {
      "price": 57.91,
      "change": -0.65,
      "pct": -1.11
    },
    "copper": {
      "price": 6.2735,
      "change": 0.064,
      "pct": 1.0307
    },
    "wti": {
      "price": 78.15,
      "change": 3.86,
      "pct": 5.1959
    },
    "brent": {
      "price": 83.43,
      "change": 4.34,
      "pct": 5.4874
    },
    "natgas": {
      "price": 2.882,
      "change": -0.022,
      "pct": -0.7576
    }
  },
  "fear_greed": {
    "score": 61
  },
  "weekend": {
    "nasdaq": {
      "price": 29205.4,
      "change": -629.7,
      "pct": -2.11
    },
    "oil": {
      "price": 7773.7,
      "change": 45.6,
      "pct": 0.59
    }
  }
}