{
  "updated": "2026-07-17T17:35:40Z",
  "quotes": {
    "dow": {
      "price": 52366.3984,
      "change": -186.5716,
      "pct": -0.355
    },
    "sp500": {
      "price": 7489.3398,
      "change": -44.4302,
      "pct": -0.5897
    },
    "nasdaq": {
      "price": 28827.4844,
      "change": -198.2856,
      "pct": -0.6831
    },
    "russell": {
      "price": 2971.896,
      "change": -2.03,
      "pct": -0.0683
    },
    "vix": {
      "price": 17.96,
      "change": 1.25,
      "pct": 7.4806
    },
    "kospi": {
      "price": 6820.6001,
      "change": -463.8099,
      "pct": -6.3672
    },
    "kospi200": {
      "price": 1080.36,
      "change": -83.54,
      "pct": -7.1776
    },
    "gold": {
      "price": 4019.5,
      "change": 23.8,
      "pct": 0.5956
    },
    "silver": {
      "price": 56.335,
      "change": 0.705,
      "pct": 1.2673
    },
    "copper": {
      "price": 6.2735,
      "change": 0.041,
      "pct": 0.6578
    },
    "wti": {
      "price": 81.66,
      "change": 2.5,
      "pct": 3.1582
    },
    "brent": {
      "price": 87.84,
      "change": 2.79,
      "pct": 3.2804
    },
    "natgas": {
      "price": 2.917,
      "change": 0.055,
      "pct": 1.9217
    }
  },
  "fear_greed": {
    "score": 56
  },
  "weekend": {
    "nasdaq": {
      "price": 28828.3,
      "change": -135.0,
      "pct": -0.47
    },
    "oil": {
      "price": 8153.6,
      "change": 326.9,
      "pct": 4.17
    }
  }
}