{
  "updated": "2026-06-10T22:00:33Z",
  "quotes": {
    "dow": {
      "price": 49918.7812,
      "change": -953.3288,
      "pct": -1.874
    },
    "sp500": {
      "price": 7266.9902,
      "change": -119.6598,
      "pct": -1.6199
    },
    "nasdaq": {
      "price": 28508.0273,
      "change": -576.4727,
      "pct": -1.9821
    },
    "russell": {
      "price": 2835.4622,
      "change": -31.5608,
      "pct": -1.1008
    },
    "vix": {
      "price": 22.22,
      "change": 2.35,
      "pct": 11.8269
    },
    "kospi": {
      "price": 7730.82,
      "change": -366.11,
      "pct": -4.5216
    },
    "kospi200": {
      "price": 1227.12,
      "change": -66.28,
      "pct": -5.1245
    },
    "gold": {
      "price": 4094.1001,
      "change": -114.1001,
      "pct": -2.7114
    },
    "silver": {
      "price": 63.5,
      "change": -0.74,
      "pct": -1.1519
    },
    "copper": {
      "price": 6.1995,
      "change": -0.113,
      "pct": -1.7901
    },
    "wti": {
      "price": 91.85,
      "change": 3.24,
      "pct": 3.6565
    },
    "brent": {
      "price": 94.71,
      "change": 2.82,
      "pct": 3.0689
    },
    "natgas": {
      "price": 3.185,
      "change": 0.058,
      "pct": 1.8548
    }
  },
  "fear_greed": {
    "score": 39
  },
  "weekend": {
    "nasdaq": {
      "price": 28393.8,
      "change": -14.3,
      "pct": -0.05
    },
    "oil": {
      "price": 9033.2,
      "change": 150.9,
      "pct": 1.69
    }
  }
}