{
  "updated": "2026-06-30T10:18:46Z",
  "quotes": {
    "dow": {
      "price": 52182.7383,
      "change": 306.6283,
      "pct": 0.5911
    },
    "sp500": {
      "price": 7440.4302,
      "change": 86.4102,
      "pct": 1.175
    },
    "nasdaq": {
      "price": 29774.75,
      "change": 656.512,
      "pct": 2.2546
    },
    "russell": {
      "price": 3010.4199,
      "change": 0.3354,
      "pct": 0.0111
    },
    "vix": {
      "price": 17.61,
      "change": -0.04,
      "pct": -0.2266
    },
    "kospi": {
      "price": 8476.4805,
      "change": 81.8305,
      "pct": 0.9748
    },
    "kospi200": {
      "price": 1370.73,
      "change": 18.19,
      "pct": 1.3449
    },
    "gold": {
      "price": 4036.0,
      "change": 52.2,
      "pct": 1.3103
    },
    "silver": {
      "price": 59.22,
      "change": 1.525,
      "pct": 2.6432
    },
    "copper": {
      "price": 6.238,
      "change": 0.062,
      "pct": 1.0039
    },
    "wti": {
      "price": 70.97,
      "change": 0.62,
      "pct": 0.8813
    },
    "brent": {
      "price": 74.2,
      "change": 0.61,
      "pct": 0.8289
    },
    "natgas": {
      "price": 3.219,
      "change": 0.055,
      "pct": 1.7383
    }
  },
  "fear_greed": {
    "score": 54
  },
  "weekend": {
    "nasdaq": {
      "price": 29809.9,
      "change": 114.2,
      "pct": 0.38
    },
    "oil": {
      "price": 7069.1,
      "change": 50.1,
      "pct": 0.71
    }
  }
}