{
  "updated": "2026-06-03T02:03:40Z",
  "quotes": {
    "dow": {
      "price": 51307.7891,
      "change": 228.9091,
      "pct": 0.4481
    },
    "sp500": {
      "price": 7609.7798,
      "change": 9.8198,
      "pct": 0.1292
    },
    "nasdaq": {
      "price": 30660.6016,
      "change": 146.7406,
      "pct": 0.4809
    },
    "russell": {
      "price": 2931.9634,
      "change": 26.2012,
      "pct": 0.9017
    },
    "vix": {
      "price": 15.77,
      "change": -0.28,
      "pct": -1.7445
    },
    "kospi": {
      "price": 8801.4902,
      "change": 13.1102,
      "pct": 0.1492
    },
    "kospi200": {
      "price": 1407.23,
      "change": 7.32,
      "pct": 0.5229
    },
    "gold": {
      "price": 4502.6001,
      "change": -25.7998,
      "pct": -0.5697
    },
    "silver": {
      "price": 74.995,
      "change": -0.53,
      "pct": -0.7018
    },
    "copper": {
      "price": 6.652,
      "change": 0.086,
      "pct": 1.3098
    },
    "wti": {
      "price": 94.87,
      "change": 3.42,
      "pct": 3.7398
    },
    "brent": {
      "price": 97.01,
      "change": 2.63,
      "pct": 2.7866
    },
    "natgas": {
      "price": 3.163,
      "change": -0.024,
      "pct": -0.7531
    }
  },
  "fear_greed": {
    "score": 69
  },
  "weekend": {
    "nasdaq": {
      "price": 30607.2,
      "change": -68.2,
      "pct": -0.22
    },
    "oil": {
      "price": 9311.7,
      "change": 92.3,
      "pct": 1.0
    }
  }
}