{
  "updated": "2026-05-14T01:30:41Z",
  "quotes": {
    "dow": {
      "price": 49693.1992,
      "change": -67.3608,
      "pct": -0.1354
    },
    "sp500": {
      "price": 7444.25,
      "change": 43.29,
      "pct": 0.5849
    },
    "nasdaq": {
      "price": 29366.9434,
      "change": 302.1444,
      "pct": 1.0396
    },
    "russell": {
      "price": 2843.9319,
      "change": 1.1009,
      "pct": 0.0387
    },
    "vix": {
      "price": 17.87,
      "change": -0.12,
      "pct": -0.667
    },
    "kospi": {
      "price": 7963.3799,
      "change": 117.0898,
      "pct": 1.4923
    },
    "kospi200": {
      "price": 1241.7,
      "change": 20.24,
      "pct": 1.657
    },
    "gold": {
      "price": 4697.2998,
      "change": -5.7002,
      "pct": -0.1212
    },
    "silver": {
      "price": 87.945,
      "change": 0.67,
      "pct": 0.7677
    },
    "copper": {
      "price": 6.6015,
      "change": -0.045,
      "pct": -0.677
    },
    "wti": {
      "price": 101.08,
      "change": 0.0,
      "pct": 0.0
    },
    "brent": {
      "price": 105.68,
      "change": -0.85,
      "pct": -0.7979
    },
    "natgas": {
      "price": 2.874,
      "change": 0.053,
      "pct": 1.8788
    }
  },
  "fear_greed": {
    "score": 65
  },
  "weekend": {
    "nasdaq": {
      "price": 29528.6,
      "change": 120.3,
      "pct": 0.41
    },
    "oil": {
      "price": 9731.2,
      "change": 1.9,
      "pct": 0.02
    }
  }
}