{
  "updated": "2026-04-27T16:06:07Z",
  "quotes": {
    "dow": {
      "price": 49137.0391,
      "change": -89.3594,
      "pct": -0.1815
    },
    "sp500": {
      "price": 7158.8301,
      "change": -5.46,
      "pct": -0.0762
    },
    "nasdaq": {
      "price": 27223.9219,
      "change": -79.7441,
      "pct": -0.2921
    },
    "russell": {
      "price": 2784.9221,
      "change": -2.0349,
      "pct": -0.073
    },
    "vix": {
      "price": 18.7,
      "change": 0.01,
      "pct": 0.0535
    },
    "kospi": {
      "price": 6615.03,
      "change": 139.4,
      "pct": 2.1527
    },
    "kospi200": {
      "price": 995.33,
      "change": 23.46,
      "pct": 2.4139
    },
    "gold": {
      "price": 4687.6001,
      "change": -52.1997,
      "pct": -1.1013
    },
    "silver": {
      "price": 75.01,
      "change": -1.35,
      "pct": -1.7679
    },
    "copper": {
      "price": 6.062,
      "change": -0.004,
      "pct": -0.0659
    },
    "wti": {
      "price": 96.38,
      "change": 1.06,
      "pct": 1.112
    },
    "brent": {
      "price": 101.63,
      "change": 1.27,
      "pct": 1.2654
    },
    "natgas": {
      "price": 2.767,
      "change": 0.079,
      "pct": 2.939
    }
  },
  "fear_greed": {
    "score": 67
  },
  "weekend": {
    "nasdaq": {
      "price": 27195.1,
      "change": -88.0,
      "pct": -0.32
    },
    "oil": {
      "price": 9497.8,
      "change": 110.5,
      "pct": 1.17
    }
  }
}