{
  "updated": "2026-04-28T15:32:26Z",
  "quotes": {
    "dow": {
      "price": 49219.1094,
      "change": 46.2188,
      "pct": 0.094
    },
    "sp500": {
      "price": 7117.54,
      "change": -56.4697,
      "pct": -0.7871
    },
    "nasdaq": {
      "price": 26884.8047,
      "change": -420.8733,
      "pct": -1.5413
    },
    "russell": {
      "price": 2757.3638,
      "change": -31.1313,
      "pct": -1.1164
    },
    "vix": {
      "price": 18.39,
      "change": 0.36,
      "pct": 1.9967
    },
    "kospi": {
      "price": 6641.02,
      "change": 25.99,
      "pct": 0.3929
    },
    "kospi200": {
      "price": 999.03,
      "change": 3.7,
      "pct": 0.3717
    },
    "gold": {
      "price": 4582.5,
      "change": -103.1001,
      "pct": -2.2004
    },
    "silver": {
      "price": 73.2,
      "change": -1.435,
      "pct": -1.9227
    },
    "copper": {
      "price": 5.972,
      "change": -0.105,
      "pct": -1.7278
    },
    "wti": {
      "price": 99.51,
      "change": 1.94,
      "pct": 1.9883
    },
    "brent": {
      "price": 104.06,
      "change": 1.33,
      "pct": 1.2947
    },
    "natgas": {
      "price": 2.71,
      "change": -0.01,
      "pct": -0.3676
    }
  },
  "fear_greed": {
    "score": 65
  },
  "weekend": {
    "nasdaq": {
      "price": 26930.6,
      "change": -334.1,
      "pct": -1.22
    },
    "oil": {
      "price": 9774.4,
      "change": 275.3,
      "pct": 2.89
    }
  }
}